ComputationalStatisticsInPython/README.md
ComputationalStatisticsInPython/__init__.py
ComputationalStatisticsInPython/__main__.py
ComputationalStatisticsInPython/file.epub
ComputationalStatisticsInPython/index.html
ComputationalStatisticsInPython/css/__init__.py
ComputationalStatisticsInPython/css/annotations.css
ComputationalStatisticsInPython/css/main.css
ComputationalStatisticsInPython/css/normalize.css
ComputationalStatisticsInPython/css/popup.css
ComputationalStatisticsInPython/font/__init__.py
ComputationalStatisticsInPython/font/fontello.eot
ComputationalStatisticsInPython/font/fontello.svg
ComputationalStatisticsInPython/font/fontello.ttf
ComputationalStatisticsInPython/font/fontello.woff
ComputationalStatisticsInPython/img/__init__.py
ComputationalStatisticsInPython/img/annotator-glyph-sprite.png
ComputationalStatisticsInPython/img/annotator-icon-sprite.png
ComputationalStatisticsInPython/img/apple-touch-icon.png
ComputationalStatisticsInPython/img/cancelfullscreen.png
ComputationalStatisticsInPython/img/close.png
ComputationalStatisticsInPython/img/fullscreen.png
ComputationalStatisticsInPython/img/loader.gif
ComputationalStatisticsInPython/img/menu-icon.png
ComputationalStatisticsInPython/img/save.png
ComputationalStatisticsInPython/img/saved.png
ComputationalStatisticsInPython/img/settings-s.png
ComputationalStatisticsInPython/img/settings.png
ComputationalStatisticsInPython/img/star.png
ComputationalStatisticsInPython/js/__init__.py
ComputationalStatisticsInPython/js/epub.js
ComputationalStatisticsInPython/js/epub.min.js
ComputationalStatisticsInPython/js/epub.min.map
ComputationalStatisticsInPython/js/hooks.min.js
ComputationalStatisticsInPython/js/hooks.min.map
ComputationalStatisticsInPython/js/reader.js
ComputationalStatisticsInPython/js/reader.js.map
ComputationalStatisticsInPython/js/reader.min.js
ComputationalStatisticsInPython/js/reader.min.map
ComputationalStatisticsInPython/js/hooks/__init__.py
computational_statistics_in_python-2024.3.2.0.dist-info/METADATA
computational_statistics_in_python-2024.3.2.0.dist-info/WHEEL
computational_statistics_in_python-2024.3.2.0.dist-info/entry_points.txt
computational_statistics_in_python-2024.3.2.0.dist-info/top_level.txt
computational_statistics_in_python-2024.3.2.0.dist-info/RECORD
